{
  "product_name": "XBO 1000 W/HTP OFR",
  "family_color_temperature_k": 6000.0,
  "family_power_min_w": 450.0,
  "family_power_max_w": 10000.0,
  "family_color_rendering_index_text": "Ra >",
  "application_areas": [
    "Klassische 35-mm-Filmprojektion",
    "Digitale Film- und Videoprojektion",
    "Architektur- und Effektlicht („Light Finger“)",
    "Sonnensimulation"
  ],
  "product_family_benefits": [
    "Kurzbogen mit sehr hoher Leuchtdichte für hellere Leinwandausleuchtung",
    "Konstante Farbtemperatur von 6.000 K über die gesamte Lebensdauer der Lampe",
    "Einfach zu warten",
    "Hohe Lichtbogenstabilität",
    "Sofort Licht auf der Leinwand dank Heißwiederzündungsfunktion",
    "Breiter Dimmbereich"
  ],
  "nominal_current_a": 45.0,
  "current_control_range_min_a": 30.0,
  "current_control_range_max_a": 55.0,
  "nominal_power_w": 1000.0,
  "nominal_voltage_v": 21.0,
  "diameter_mm": 46.0,
  "length_mm": 330.0,
  "length_with_base_without_pin_mm": 277.0,
  "light_center_length_lcl_mm": 123.0,
  "electrode_gap_cold_mm": 4.8,
  "product_weight_g": 331.0,
  "cable_length_mm": 0.0,
  "max_permissible_pinch_temperature_celsius": 230.0,
  "lifespan_h": 2400,
  "base_anode_standard_designation": "SFa25-14",
  "base_cathode_standard_designation": "SFc25-14",
  "cooling": "Forciert",
  "burning_position": "s30/p30",
  "reach_declaration_date": "2023-02-10",
  "primary_product_eans": [
    "4008321081353",
    "4062172030243"
  ],
  "reach_candidate_substance_name": "Lead",
  "reach_candidate_substance_cas": "7439-92-1",
  "scip_numbers": [
    "4a09dcc0-a0da-4682-93fa-303d254e4c80"
  ],
  "packaging_product_code": "4062172030243",
  "packaging_product_description": "XBO 1000 W/HTP\nOFR",
  "packaging_unit_pieces": 1,
  "packaging_dimension_length_mm": 1500.0,
  "packaging_dimension_width_mm": 204.0,
  "packaging_dimension_height_mm": 204.0,
  "packaging_volume_dm3": 20.81,
  "packaging_gross_weight_g": 1127.0
}